[
  {
    "air_conditioned": "true",
    "cafe_url": "https://www.foody.vn/ho-chi-minh/regina-coffee-ca-phe-84-nguyen-du.a3dhyu",
    "name": "Regina Coffee",
    "open_late": "false",
    "opens_early": "true",
    "outdoor_seating": "true",
    "parking": "true",
    "power_outlets": "false",
    "price_tier": "",
    "quiet": "",
    "rating": "0",
    "review_count": "0",
    "street_address": "84 Nguyễn Du, Phường Bến Nghé, Quận 1, TP.HCM",
    "study_friendly": "",
    "takeaway": "true",
    "wifi": "true"
  },
  {
    "air_conditioned": true,
    "cafe_url": "https://www.foody.vn/ho-chi-minh/uptown-coffee-food-74-suong-nguyet-anh",
    "name": "Uptown Coffee & Food",
    "open_late": true,
    "opens_early": true,
    "outdoor_seating": true,
    "parking": true,
    "power_outlets": false,
    "price_tier": "Mid-range",
    "quiet": false,
    "rating": 3.65,
    "review_count": 5,
    "street_address": "74 Sương Nguyệt Ánh, P. Bến Thành, Quận 1, TP. HCM",
    "study_friendly": true,
    "takeaway": true,
    "wifi": true
  },
  {
    "air_conditioned": "true",
    "cafe_url": "https://www.foody.vn/ho-chi-minh/guta-cafe-116c-nguyen-dinh-chieu",
    "name": "Guta Cafe",
    "open_late": "true",
    "opens_early": "false",
    "outdoor_seating": "true",
    "parking": "true",
    "power_outlets": "false",
    "price_tier": "Budget",
    "quiet": "false",
    "rating": "3.5",
    "review_count": "",
    "street_address": "116C Nguyễn Đình Chiểu, P. Đa Kao, Quận 1, TP.HCM",
    "study_friendly": "false",
    "takeaway": "true",
    "wifi": "true"
  },
  {
    "air_conditioned": true,
    "cafe_url": "https://www.foody.vn/ho-chi-minh/things-cafe",
    "name": "Things Cafe",
    "open_late": false,
    "opens_early": false,
    "outdoor_seating": true,
    "parking": true,
    "power_outlets": true,
    "price_tier": "Budget",
    "quiet": true,
    "rating": 4.15,
    "review_count": 70,
    "street_address": "14 Tôn Thất Đạm, Phường Bến Nghé, Quận 1, TP.HCM",
    "study_friendly": true,
    "takeaway": true,
    "wifi": true
  },
  {
    "air_conditioned": true,
    "cafe_url": "https://www.foody.vn/ho-chi-minh/73-dong-du",
    "name": "Đông Du - Trà Sữa & Cà Phê",
    "open_late": true,
    "opens_early": false,
    "outdoor_seating": true,
    "parking": true,
    "power_outlets": true,
    "price_tier": "Budget",
    "quiet": true,
    "rating": 3.8,
    "review_count": 37,
    "street_address": "73 Đông Du, Phường Bến Nghé, Quận 1, TP.HCM",
    "study_friendly": true,
    "takeaway": true,
    "wifi": true
  },
  {
    "air_conditioned": true,
    "cafe_url": "https://www.foody.vn/ho-chi-minh/1st-garden-cafe-bistro",
    "name": "1st. Garden - Cafe & Bistro",
    "open_late": true,
    "opens_early": true,
    "outdoor_seating": true,
    "parking": true,
    "power_outlets": "",
    "price_tier": "Budget",
    "quiet": true,
    "rating": 4.4,
    "review_count": 71,
    "street_address": "4B-5A, 1st floor, Saigon Centre, 3-5-7 Đường 18 Tháng 4, Phường Bến Nghé, Quận 1, TP.HCM",
    "study_friendly": true,
    "takeaway": true,
    "wifi": true
  },
  {
    "air_conditioned": "true",
    "cafe_url": "https://www.foody.vn/ho-chi-minh/paris-deli-cafe-le-loi",
    "name": "Paris Deli Cafe - Lê Lợi",
    "open_late": "true",
    "opens_early": "",
    "outdoor_seating": "true",
    "parking": "true",
    "power_outlets": "true",
    "price_tier": "$$",
    "quiet": "",
    "rating": "3.9",
    "review_count": "14",
    "street_address": "65 Lê Lợi, Phường Bến Nghé, Quận 1, TP.HCM",
    "study_friendly": "true",
    "takeaway": "true",
    "wifi": "true"
  },
  {
    "air_conditioned": true,
    "cafe_url": "https://www.foody.vn/ho-chi-minh/trung-nguyen-coffee-80-dong-khoi",
    "name": "Trung Nguyên Legend Coffee",
    "open_late": false,
    "opens_early": true,
    "outdoor_seating": true,
    "parking": true,
    "power_outlets": "",
    "price_tier": "Mid-range",
    "quiet": true,
    "rating": 3.95,
    "review_count": 36,
    "street_address": "80 Đồng Khởi, Phường Bến Nghé, Quận 1, TP.HCM",
    "study_friendly": true,
    "takeaway": true,
    "wifi": true
  }
]
